{
    "Legible": {
        "definition": "Clear enough to read",
        "partOfSpeech": "adjective",
        "synonyms": [],
        "antonyms": [],
        "examples": []
    },

    "Linger": {
        "definition": "Be slow or reluctant to leave, spend a long time",
        "partOfSpeech": "verb",
        "synonyms": [],
        "antonyms": [],
        "examples": []
    },

    "Languish": {
        "definition": "Become weak or feeble, be forced to remain in an unpleasant place",
        "partOfSpeech": "verb",
        "synonyms": [],
        "antonyms": [],
        "examples": []
    },

    "Loathe": {
        "definition": "Feel hatred and disgust for",
        "partOfSpeech": "verb",
        "synonyms": [],
        "antonyms": [],
        "examples": []
    },

    "Leverage": {
        "definition": "The power of influence",
        "partOfSpeech": "noun",
        "synonyms": [],
        "antonyms": [],
        "examples": []
    }
}